examples/MARLANN/pipe_defs.vh
localparam NOP         = 0;
localparam MEM1        = 1;
localparam MEM2        = 2;
localparam ADD         = 3;
localparam MULT        = 4;
localparam WRITE       = 5;

examples/MARLANN/pipeline.v
`default_nettype none
module pipeline (
    input wire clk,
    input wire [7:0] inst
);

    `include "pipe_defs.vh"

    wire memory_1;
    wire memory_2;
    wire add;
    wire mult;
    wire write;

    wire mem_access = memory_1 | memory_2 | write;
    wire [2:0] sum_mem_access = memory_1 + memory_2 + write;
    wire collision = sum_mem_access > 1;

    reg [7:0] inst1 = 0;
    reg [7:0] inst2 = 0;
    reg [7:0] inst3 = 0;
    reg [7:0] inst4 = 0;
    reg [7:0] inst5 = 0;
   
    always @(posedge clk) begin
        inst1 <= inst;
        inst2 <= inst1;
        inst3 <= inst2;
        inst4 <= inst3;
        inst5 <= inst4;

    end

    assign memory_1 = inst1 == MEM1;
    assign memory_2 = inst2 == MEM2;
    assign add      = inst3 == ADD;
    assign mult     = inst4 == MULT;
    assign write    = inst5 == WRITE;

endmodule

examples/MARLANN/test.v
module test;

    reg clk = 0;
    reg [7:0] inst = NOP;

    `include "pipe_defs.vh"

    initial begin
        $dumpfile("test.vcd");
        $dumpvars(0,test);
        # 1
        inst <= MEM1;
        # 2
        inst <= MEM2;
        # 2
        inst <= ADD;
        # 2
        inst <= MULT;
        # 2
        inst <= WRITE;
        # 2
        inst <= NOP;
        # 2
        inst <= NOP;
        # 2
        inst <= NOP;
        # 2
        inst <= MEM1;
        # 2
        inst <= MEM1;
        # 2
        inst <= NOP;
        # 40
        $finish;
    end

    pipeline pipe_0(.clk(clk), .inst(inst));

    /* Make a regular pulsing clock. */
    always #1 clk = !clk;

endmodule // test

examples/MARLANN/test.vcd
$date
	Thu Jan 31 13:59:48 2019
$end
$version
	Icarus Verilog
$end
$timescale
	1s
$end
$scope module test $end
$var reg 1 ! clk $end
$var reg 8 " inst [7:0] $end
$scope module pipe_0 $end
$var wire 1 ! clk $end
$var wire 8 # inst [7:0] $end
$var wire 1 $ mem_access $end
$var wire 1 % write $end
$var wire 3 & sum_mem_access [2:0] $end
$var wire 1 ' mult $end
$var wire 1 ( memory_2 $end
$var wire 1 ) memory_1 $end
$var wire 1 * collision $end
$var wire 1 + add $end
$var reg 8 , inst1 [7:0] $end
$var reg 8 - inst2 [7:0] $end
$var reg 8 . inst3 [7:0] $end
$var reg 8 / inst4 [7:0] $end
$var reg 8 0 inst5 [7:0] $end
$upscope $end
$upscope $end
$enddefinitions $end
#0
$dumpvars
b0 0
b0 /
b0 .
b0 -
b0 ,
0+
0*
0)
0(
0'
b0 &
0%
0$
b0 #
b0 "
0!
$end
#1
b1 "
b1 #
1!
#2
0!
#3
1$
b1 &
1)
b1 ,
b10 "
b10 #
1!
#4
0!
#5
0$
b1 -
b0 &
0)
b10 ,
b11 "
b11 #
1!
#6
0!
#7
1$
b1 .
b1 &
1(
b10 -
b11 ,
b100 "
b100 #
1!
#8
0!
#9
0$
b1 /
b10 .
b0 &
0(
b11 -
b100 ,
b101 "
b101 #
1!
#10
0!
#11
b1 0
b10 /
1+
b11 .
b100 -
b101 ,
b0 "
b0 #
1!
#12
0!
#13
b10 0
b11 /
0+
b100 .
b101 -
b0 ,
1!
#14
0!
#15
b11 0
1'
b100 /
b101 .
b0 -
1!
#16
0!
#17
b100 0
0'
b101 /
b0 .
b1 "
b1 #
1!
#18
0!
#19
1$
1*
1%
b101 0
b0 /
b10 &
1)
b1 ,
1!
#20
0!
#21
0*
b1 &
0%
b0 0
b1 -
b0 "
b0 #
1!
#22
0!
#23
0$
b1 .
b0 &
0)
b0 ,
1!
#24
0!
#25
b1 /
b0 -
1!
#26
0!
#27
b1 0
b0 .
1!
#28
0!
#29
b0 /
1!
#30
0!
#31
b0 0
1!
